Metadata-Version: 1.0
Name: pacoteexemplo1
Version: 0.1.2
Summary: Exemplo de pacote PyPI
Home-page: UNKNOWN
Author: Fábio Minutti teixeira
Author-email: fabiomt92@hotmail.com
License: MIT License
Keywords: Pacote
Platform: UNKNOWN
